{
      "type": "Feature",
      "properties": {
        "city": "01530",
        "first_city": "Alma",
        "id": 37
      },
      "geometry": {
        "type": "Polygon",
        "coordinates": [
          [
            [
              -106.07376057055323,
              39.28355506115904
            ],
            [
              -106.07376059023186,
              39.283555062761685
            ],
            [
              -106.07376060921204,
              39.28355506819941
            ],
            [
              -106.07376062675394,
              39.28355507726025
            ],
            [
              -106.0737606421737,
              39.283555089591005
            ],
            [
              -106.07376065487026,
              39.28355510471099
            ],
            [
              -106.07376066434868,
              39.28355512203082
            ],
            [
              -106.07376067023947,
              39.283555140875315
            ],
            [
              -106.073760672313,
              39.283555160509906
            ],
            [
              -106.07377205343633,
              39.28535133501978
            ],
            [
              -106.07377205165034,
              39.28535135447901
            ],
            [
              -106.0737720461141,
              39.28535137321938
            ],
            [
              -106.07377203703903,
              39.285351390525285
            ],
            [
              -106.07377202477166,
              39.2853514057359
            ],
            [
              -106.07377200978041,
              39.28535141827041
            ],
            [
              -106.07377199263775,
              39.28535142765018
            ],
            [
              -106.07377197399823,
              39.285351433517036
            ],
            [
              -106.07377195457364,
              39.28535143564696
            ],
            [
              -106.07356837778453,
              39.285353747022235
            ],
            [
              -106.07372770872574,
              39.2856719161211
            ],
            [
              -106.07394400042516,
              39.28609347328887
            ],
            [
              -106.07399880709701,
              39.28618591779466
            ],
            [
              -106.07405228889438,
              39.28625577563854
            ],
            [
              -106.07410806483453,
              39.28632068041599
            ],
            [
              -106.07417144149007,
              39.28637533804983
            ],
            [
              -106.07426080602669,
              39.28643905731401
            ],
            [
              -106.07436419896362,
              39.28650115708916
            ],
            [
              -106.07447253385952,
              39.28656359035756
            ],
            [
              -106.07462464071664,
              39.28665124815511
            ],
            [
              -106.07480332665546,
              39.286752167292995
            ],
            [
              -106.0748033317857,
              39.286752170396944
            ],
            [
              -106.07492685524231,
              39.286832060422
            ],
            [
              -106.0749268641403,
              39.28683206689804
            ],
            [
              -106.07505537365489,
              39.286936883575926
            ],
            [
              -106.07505537883885,
              39.28693688811019
            ],
            [
              -106.07515748046404,
              39.28703259595291
            ],
            [
              -106.07515748911369,
              39.287032605153804
            ],
            [
              -106.07520665932397,
              39.287092018394375
            ],
            [
              -106.07529643967563,
              39.28718417508839
            ],
            [
              -106.0754004580851,
              39.28727540258987
            ],
            [
              -106.07549922213927,
              39.28735681134036
            ],
            [
              -106.07560862980664,
              39.287444167028674
            ],
            [
              -106.07560863304192,
              39.28744416972537
            ],
            [
              -106.07566303252217,
              39.28749148965455
            ],
            [
              -106.07617887538409,
              39.28789900828754
            ],
            [
              -106.07637906420177,
              39.28803297825028
            ],
            [
              -106.0765157107252,
              39.28812442493465
            ],
            [
              -106.07664708225886,
              39.288212340212795
            ],
            [
              -106.07664708628012,
              39.28821234304957
            ],
            [
              -106.07673014652603,
              39.28827405328248
            ],
            [
              -106.07684028597163,
              39.28834970852689
            ],
            [
              -106.07684029663847,
              39.28834971697734
            ],
            [
              -106.07692096521778,
              39.28842309005711
            ],
            [
              -106.07692097330717,
              39.2884230983185
            ],
            [
              -106.07702226162692,
              39.28853927655169
            ],
            [
              -106.0770222705915,
              39.28853928853885
            ],
            [
              -106.07710669674582,
              39.288671817501964
            ],
            [
              -106.07710670336942,
              39.28867182969019
            ],
            [
              -106.07715561152118,
              39.28877892866185
            ],
            [
              -106.0771556128208,
              39.28877893163443
            ],
            [
              -106.07721921524472,
              39.28893108610457
            ],
            [
              -106.07729307836355,
              39.28908755375096
            ],
            [
              -106.0773573434272,
              39.289179193331584
            ],
            [
              -106.07741828064017,
              39.28925587403346
            ],
            [
              -106.07753861194361,
              39.289364033487786
            ],
            [
              -106.07768144572371,
              39.28947515773938
            ],
            [
              -106.07780133074962,
              39.28955463461266
            ],
            [
              -106.07796048664135,
              39.28965371946134
            ],
            [
              -106.07810485150843,
              39.28972163240179
            ],
            [
              -106.07826545417247,
              39.28978052850738
            ],
            [
              -106.07833831279346,
              39.28980049084701
            ],
            [
              -106.0783383130001,
              39.289800490903865
            ],
            [
              -106.07844575898373,
              39.289830177455784
            ],
            [
              -106.07859648152736,
              39.28987008284637
            ],
            [
              -106.07876757836135,
              39.28990331358622
            ],
            [
              -106.0789165759683,
              39.289919746325815
            ],
            [
              -106.07905962251128,
              39.28993222457443
            ],
            [
              -106.07933714838593,
              39.28995465776104
            ],
            [
              -106.07933714926496,
              39.28995465783599
            ],
            [
              -106.07964728512188,
              39.28998248297858
            ],
            [
              -106.08006775019801,
              39.290013709944716
            ],
            [
              -106.08006775084758,
              39.29001370999508
            ],
            [
              -106.08041478552272,
              39.29004175804579
            ],
            [
              -106.08063652037289,
              39.290054324758536
            ],
            [
              -106.08063652833356,
              39.29005432553006
            ],
            [
              -106.08079237414276,
              39.290075749843304
            ],
            [
              -106.08079238214846,
              39.290075751277705
            ],
            [
              -106.08096727048267,
              39.290114486941896
            ],
            [
              -106.08096728371913,
              39.29011449084904
            ],
            [
              -106.08113428492615,
              39.29017660612819
            ],
            [
              -106.08113429841762,
              39.29017661232194
            ],
            [
              -106.08128749109395,
              39.290261234989984
            ],
            [
              -106.081287503015,
              39.29026124272898
            ],
            [
              -106.08142794630756,
              39.290367328947625
            ],
            [
              -106.08142794797878,
              39.290367330237935
            ],
            [
              -106.0815746103941,
              39.29048305725543
            ],
            [
              -106.08169151417235,
              39.2905753018519
            ],
            [
              -106.08184533134288,
              39.29069284706737
            ],
            [
              -106.08191115047302,
              39.29073143476508
            ],
            [
              -106.08198970621054,
              39.290767635257815
            ],
            [
              -106.08209393874597,
              39.29080230098415
            ],
            [
              -106.08216575512664,
              39.29081859542473
            ],
            [
              -106.08229954567187,
              39.290838335231484
            ],
            [
              -106.08250816622994,
              39.29086747003116
            ],
            [
              -106.08283060479843,
              39.29091249839025
            ],
            [
              -106.08288261366093,
              39.2909197613823
            ],
            [
              -106.08308581047653,
              39.290096550492066
            ],
            [
              -106.08308581651814,
              39.29009653309331
            ],
            [
              -106.08308582564813,
              39.290096517097666
            ],
            [
              -106.08308583755681,
              39.29009650304772
            ],
            [
              -106.08308585184022,
              39.29009649142008
            ],
            [
              -106.08308586801382,
              39.29009648260917
            ],
            [
              -106.083085885529,
              39.29009647691388
            ],
            [
              -106.0830859037916,
              39.2900964745274
            ],
            [
              -106.08308592218211,
              39.29009647553068
            ],
            [
              -106.08394266928981,
              39.29022308755181
            ],
            [
              -106.08394268926952,
              39.29022309265363
            ],
            [
              -106.08394270777801,
              39.290223101745006
            ],
            [
              -106.08394272402828,
              39.29022311443935
            ],
            [
              -106.08394273732932,
              39.29022313019687
            ],
            [
              -106.08394274711556,
              39.290223148347536
            ],
            [
              -106.08394275297087,
              39.29022316811955
            ],
            [
              -106.08394275464627,
              39.29022318867218
            ],
            [
              -106.08394275207053,
              39.290223209131476
            ],
            [
              -106.08378770638012,
              39.29088982092471
            ],
            [
              -106.08378770082437,
              39.29088983782571
            ],
            [
              -106.08378769236165,
              39.290889853474745
            ],
            [
              -106.0837876812598,
              39.29088986737652
            ],
            [
              -106.08378766787024,
              39.29088987909102
            ],
            [
              -106.08361848864509,
              39.29101315260851
            ],
            [
              -106.08361027608215,
              39.29117751066691
            ],
            [
              -106.08361027293695,
              39.29117753103915
            ],
            [
              -106.08361026568149,
              39.29117755033368
            ],
            [
              -106.08361025462405,
              39.29117756773063
            ],
            [
              -106.0836102402345,
              39.29117758249076
            ],
            [
              -106.0836102231243,
              39.291177593986895
            ],
            [
              -106.08361020402046,
              39.29117760173053
            ],
            [
              -106.08361018373476,
              39.29117760539263
            ],
            [
              -106.08361016312918,
              39.291177604817584
            ],
            [
              -106.08217304076764,
              39.29098803601295
            ],
            [
              -106.0821730357422,
              39.290988035219506
            ],
            [
              -106.08206707947969,
              39.29096853168561
            ],
            [
              -106.08206707030423,
              39.29096852954536
            ],
            [
              -106.0819503661028,
              39.29093543948214
            ],
            [
              -106.08195035907309,
              39.290935437205185
            ],
            [
              -106.08190175550801,
              39.29091768472658
            ],
            [
              -106.0819017488342,
              39.29091768201267
            ],
            [
              -106.08180222740305,
              39.29087296880938
            ],
            [
              -106.08180222614881,
              39.29087296823545
            ],
            [
              -106.08169259366521,
              39.29082188344356
            ],
            [
              -106.08169256949455,
              39.290821867567985
            ],
            [
              -106.08158164548362,
              39.29072334672975
            ],
            [
              -106.08145551260706,
              39.29062381943801
            ],
            [
              -106.08133402521295,
              39.29052795767861
            ],
            [
              -106.08121260559004,
              39.29043216818541
            ],
            [
              -106.08109093400253,
              39.29035087769227
            ],
            [
              -106.08103273758336,
              39.29032131591411
            ],
            [
              -106.08097693567332,
              39.290297457959824
            ],
            [
              -106.08091270940899,
              39.290274784645185
            ],
            [
              -106.08083709229855,
              39.290253970062
            ],
            [
              -106.08075875893407,
              39.290238520210174
            ],
            [
              -106.08064377106669,
              39.29022588267817
            ],
            [
              -106.08050849649383,
              39.29021495049713
            ],
            [
              -106.08027731858262,
              39.290197751599926
            ],
            [
              -106.08027731783876,
              39.2901977515418
            ],
            [
              -106.07889593762529,
              39.290084611439354
            ],
            [
              -106.0788959346832,
              39.290084611154555
            ],
            [
              -106.07874768392904,
              39.290068045275085
            ],
            [
              -106.07874767789326,
              39.290068044413616
            ],
            [
              -106.07860489581954,
              39.29004320264169
            ],
            [
              -106.07860489390156,
              39.29004320228869
            ],
            [
              -106.07842407842593,
              39.29000809743076
            ],
            [
              -106.0784240621467,
              39.2900080928117
            ],
            [
              -106.07833622433982,
              39.28997491173061
            ],
            [
              -106.07832991817247,
              39.29010000656702
            ],
            [
              -106.07832991815475,
              39.29010000690714
            ],
            [
              -106.0782008436803,
              39.29249799879427
            ],
            [
              -106.078200840908,
              39.292498017395715
            ],
            [
              -106.07820083470187,
              39.29249803514912
            ],
            [
              -106.07820082528143,
              39.292498051426556
            ],
            [
              -106.07820081297987,
              39.29249806565228
            ],
            [
              -106.0782007982323,
              39.29249807732313
            ],
            [
              -106.07820078156034,
              39.29249808602631
            ],
            [
              -106.07820076355368,
              39.29249809145399
            ],
            [
              -106.07820074484921,
              39.29249809341419
            ],
            [
              -106.07363833594177,
              39.2925448316066
            ],
            [
              -106.07363831581459,
              39.29254482977031
            ],
            [
              -106.07363829646772,
              39.29254482392448
            ],
            [
              -106.07363827869142,
              39.29254481430791
            ],
            [
              -106.07363826321182,
              39.29254480131342
            ],
            [
              -106.0736382506612,
              39.29254478547178
            ],
            [
              -106.07363824155225,
              39.29254476743011
            ],
            [
              -106.07363823625703,
              39.29254474792535
            ],
            [
              -106.07363823499183,
              39.29254472775422
            ],
            [
              -106.07374343214822,
              39.28981976537492
            ],
            [
              -106.07374343469267,
              39.28981974649674
            ],
            [
              -106.07374344077068,
              39.289819728443554
            ],
            [
              -106.07374345016173,
              39.28981971187043
            ],
            [
              -106.07374346252502,
              39.28981969737875
            ],
            [
              -106.07374347741197,
              39.28981968549436
            ],
            [
              -106.07374349428237,
              39.28981967664849
            ],
            [
              -106.07374351252408,
              39.28981967116212
            ],
            [
              -106.07374353147516,
              39.28981966923434
            ],
            [
              -106.07785984856373,
              39.28979502737932
            ],
            [
              -106.0777183145884,
              39.28971230921419
            ],
            [
              -106.07771831413423,
              39.28971230894715
            ],
            [
              -106.0776257816472,
              39.28965757317679
            ],
            [
              -106.07762577720115,
              39.28965757038675
            ],
            [
              -106.07752523541014,
              39.28959073671127
            ],
            [
              -106.07752523044968,
              39.28959073319179
            ],
            [
              -106.07745868448188,
              39.289540407148
            ],
            [
              -106.07745867938695,
              39.28954040302564
            ],
            [
              -106.07736367529762,
              39.28945823994266
            ],
            [
              -106.0773636708531,
              39.289458235858014
            ],
            [
              -106.0772821557711,
              39.28937865084213
            ],
            [
              -106.07728214915454,
              39.28937864372207
            ],
            [
              -106.07726042820134,
              39.28935286312968
            ],
            [
              -106.07718924657009,
              39.289280606471
            ],
            [
              -106.07718923812247,
              39.28928059670834
            ],
            [
              -106.077130071696,
              39.289202558716916
            ],
            [
              -106.07713006607801,
              39.289202550484994
            ],
            [
              -106.07708216510166,
              39.289124247867356
            ],
            [
              -106.07708215980658,
              39.28912423801244
            ],
            [
              -106.07703431698894,
              39.28902183774525
            ],
            [
              -106.0770343153247,
              39.28902183398327
            ],
            [
              -106.07699134146364,
              39.28891902862466
            ],
            [
              -106.07695138026398,
              39.288823429205344
            ],
            [
              -106.0769513794998,
              39.28882342732376
            ],
            [
              -106.0769222111543,
              39.28874946114372
            ],
            [
              -106.07689053257974,
              39.28869211530652
            ],
            [
              -106.07684672140658,
              39.288632410391784
            ],
            [
              -106.07679429546226,
              39.28856251309729
            ],
            [
              -106.07673402186485,
              39.28850084804099
            ],
            [
              -106.07668132463226,
              39.288458780683726
            ],
            [
              -106.07659279024418,
              39.28839296333881
            ],
            [
              -106.0765012816181,
              39.28833214088057
            ],
            [
              -106.07650128135595,
              39.28833214070573
            ],
            [
              -106.07639509286767,
              39.288261077610905
            ],
            [
              -106.07630422468743,
              39.28820026658611
            ],
            [
              -106.07618865037821,
              39.288122922342275
            ],
            [
              -106.07610321170246,
              39.28806574435719
            ],
            [
              -106.07610320996326,
              39.28806574316655
            ],
            [
              -106.07601033259628,
              39.28800071164992
            ],
            [
              -106.07601032651051,
              39.28800070703254
            ],
            [
              -106.07589740702393,
              39.28790802915739
            ],
            [
              -106.07551378520137,
              39.28760454534082
            ],
            [
              -106.07551378488792,
              39.287604545091824
            ],
            [
              -106.07534359230202,
              39.28746879426293
            ],
            [
              -106.07534359079827,
              39.28746879303946
            ],
            [
              -106.07523465062765,
              39.287378388705314
            ],
            [
              -106.07523464674327,
              39.28737838530886
            ],
            [
              -106.07513484040503,
              39.28728646582783
            ],
            [
              -106.07513483688071,
              39.28728646241858
            ],
            [
              -106.07505362526152,
              39.28720395304076
            ],
            [
              -106.07505361867263,
              39.28720394564752
            ],
            [
              -106.07500389607517,
              39.287142256376534
            ],
            [
              -106.0749275921067,
              39.28707009292946
            ],
            [
              -106.07483507947717,
              39.28699116809738
            ],
            [
              -106.07470992225203,
              39.28690576295742
            ],
            [
              -106.07456267866857,
              39.28682060441638
            ],
            [
              -106.0743756906325,
              39.2867128452027
            ],
            [
              -106.07421096139042,
              39.28661791363642
            ],
            [
              -106.07421095833597,
              39.286617911802935
            ],
            [
              -106.07409992932989,
              39.2865485449865
            ],
            [
              -106.0740999214416,
              39.28654853951483
            ],
            [
              -106.07400572671784,
              39.28647626592035
            ],
            [
              -106.07400571982566,
              39.28647626012077
            ],
            [
              -106.07393425646741,
              39.28641040566404
            ],
            [
              -106.07393424821325,
              39.28641039709525
            ],
            [
              -106.07387836922395,
              39.28634501304333
            ],
            [
              -106.07382935120924,
              39.28628816191152
            ],
            [
              -106.07382934289788,
              39.28628815079723
            ],
            [
              -106.0737662496886,
              39.286190288392
            ],
            [
              -106.07376624359823,
              39.2861902775105
            ],
            [
              -106.07371064226793,
              39.28607454508582
            ],
            [
              -106.07350890020805,
              39.28567433168705
            ],
            [
              -106.07334483297315,
              39.28535628545223
            ],
            [
              -106.07087654019449,
              39.28538427863705
            ],
            [
              -106.07087653873522,
              39.28538427864295
            ],
            [
              -106.0708702435859,
              39.28538425816938
            ],
            [
              -106.0718577121713,
              39.28958165734474
            ],
            [
              -106.07185771480124,
              39.28958167789904
            ],
            [
              -106.07185771313843,
              39.28958169855408
            ],
            [
              -106.07185770725422,
              39.28958171842296
            ],
            [
              -106.07185769740131,
              39.289581736652494
            ],
            [
              -106.07185768400278,
              39.28958175245993
            ],
            [
              -106.07185766763394,
              39.289581765166496
            ],
            [
              -106.07185764899766,
              39.28958177422658
            ],
            [
              -106.0718576288942,
              39.28958177925115
            ],
            [
              -106.07131323909559,
              39.289659118844355
            ],
            [
              -106.07141720109286,
              39.29031362409462
            ],
            [
              -106.07141720225668,
              39.290313643636544
            ],
            [
              -106.07141719959094,
              39.290313663030744
            ],
            [
              -106.07141719319779,
              39.29031368153396
            ],
            [
              -106.07141718332225,
              39.29031369843707
            ],
            [
              -106.07141717034281,
              39.290313713092274
            ],
            [
              -106.07141715475686,
              39.290313724937924
            ],
            [
              -106.07127438990035,
              39.2904016174815
            ],
            [
              -106.07127437229241,
              39.290401626068395
            ],
            [
              -106.07127435334823,
              39.29040163105767
            ],
            [
              -106.07127433379486,
              39.29040163225787
            ],
            [
              -106.07127431438272,
              39.29040162962291
            ],
            [
              -106.07127429585677,
              39.29040162325394
            ],
            [
              -106.07004891934075,
              39.28984077098026
            ],
            [
              -106.06934169197352,
              39.28994123248656
            ],
            [
              -106.06933678008075,
              39.289967822427364
            ],
            [
              -106.06933677473488,
              39.28996784104224
            ],
            [
              -106.06933676590101,
              39.289967858277514
            ],
            [
              -106.0693367539105,
              39.28996787348672
            ],
            [
              -106.06933673921311,
              39.28996788609935
            ],
            [
              -106.06933672236012,
              39.28996789564232
            ],
            [
              -106.06933670398367,
              39.2899679017577
            ],
            [
              -106.0678435571168,
              39.29030849438574
            ],
            [
              -106.06784353852207,
              39.29030849682356
            ],
            [
              -106.06784351979915,
              39.29030849574666
            ],
            [
              -106.06784350160657,
              39.29030849119289
            ],
            [
              -106.06784348458415,
              39.29030848332243
            ],
            [
              -106.06784346933058,
              39.29030847241207
            ],
            [
              -106.06784345638235,
              39.29030845884555
            ],
            [
              -106.06781052571557,
              39.290266736964675
            ],
            [
              -106.06781052107803,
              39.29026673058728
            ],
            [
              -106.06778148443352,
              39.290223298081095
            ],
            [
              -106.0677814752944,
              39.2902232810501
            ],
            [
              -106.06778146960234,
              39.290223262579076
            ],
            [
              -106.06778146757001,
              39.29022324335805
            ],
            [
              -106.06778146927333,
              39.29022322410507
            ],
            [
              -106.06778147464867,
              39.2902232055394
            ],
            [
              -106.06778148349521,
              39.29022318835461
            ],
            [
              -106.06778149548246,
              39.29022317319268
            ],
            [
              -106.06778151016262,
              39.29022316062003
            ],
            [
              -106.06778152698725,
              39.29022315110635
            ],
            [
              -106.06778154532783,
              39.290223145007054
            ],
            [
              -106.06837828245528,
              39.290087030987976
            ],
            [
              -106.06837267184137,
              39.290078904209885
            ],
            [
              -106.06277828476813,
              39.29087337491115
            ],
            [
              -106.06277826630465,
              39.29087337580753
            ],
            [
              -106.06277824799163,
              39.29087337329018
            ],
            [
              -106.06277823045485,
              39.29087336744514
            ],
            [
              -106.06277821429352,
              39.29087335847212
            ],
            [
              -106.0627782000599,
              39.29087334667773
            ],
            [
              -106.06277818824034,
              39.290873332465
            ],
            [
              -106.06277817923875,
              39.290873316319576
            ],
            [
              -106.06277817336267,
              39.29087329879316
            ],
            [
              -106.06176844272194,
              39.28657891670454
            ],
            [
              -106.06122521062198,
              39.28568802001827
            ],
            [
              -106.06096636803024,
              39.28548677631251
            ],
            [
              -106.06096635232373,
              39.28548676106655
            ],
            [
              -106.06096634031066,
              39.28548674276848
            ],
            [
              -106.06083926556636,
              39.285237370235656
            ],
            [
              -106.06033870295487,
              39.284968214758656
            ],
            [
              -106.06033868689094,
              39.284968203998794
            ],
            [
              -106.0603386731979,
              39.28496819034871
            ],
            [
              -106.06033866238762,
              39.28496817431867
            ],
            [
              -106.06033865486421,
              39.28496815650793
            ],
            [
              -106.06033865090892,
              39.28496813758229
            ],
            [
              -106.06033865066959,
              39.28496811824924
            ],
            [
              -106.06033865415519,
              39.28496809923149
            ],
            [
              -106.06033866123542,
              39.284968081239974
            ],
            [
              -106.06033867164558,
              39.28496806494726
            ],
            [
              -106.06033868499654,
              39.2849680509624
            ],
            [
              -106.06033870078919,
              39.28496803980819
            ],
            [
              -106.06033871843317,
              39.2849680319016
            ],
            [
              -106.06071558473332,
              39.28484127257998
            ],
            [
              -106.06047413871585,
              39.28444528172731
            ],
            [
              -106.05949067854175,
              39.28476582212109
            ],
            [
              -106.05949065990951,
              39.28476582627739
            ],
            [
              -106.05949064082698,
              39.284765826817285
            ],
            [
              -106.05949062198957,
              39.284765823721074
            ],
            [
              -106.05949060408376,
              39.28476581710161
            ],
            [
              -106.05949058776214,
              39.28476580720012
            ],
            [
              -106.05949057361951,
              39.28476579437745
            ],
            [
              -106.05949056217128,
              39.28476577910091
            ],
            [
              -106.05873417997608,
              39.28352519549433
            ],
            [
              -106.05873417132361,
              39.28352517746001
            ],
            [
              -106.05873416643345,
              39.28352515806443
            ],
            [
              -106.05873416550129,
              39.28352513808361
            ],
            [
              -106.05873416856441,
              39.283525118316994
            ],
            [
              -106.05873417550025,
              39.28352509955543
            ],
            [
              -106.05873418603132,
              39.28352508254959
            ],
            [
              -106.05873419973626,
              39.28352506797987
            ],
            [
              -106.05873421606672,
              39.28352505642922
            ],
            [
              -106.05873423436935,
              39.28352504835976
            ],
            [
              -106.05971285101435,
              39.28320608836827
            ],
            [
              -106.05951580959508,
              39.28284096149459
            ],
            [
              -106.05951580190721,
              39.28284094304116
            ],
            [
              -106.05951579804346,
              39.28284092342728
            ],
            [
              -106.05949619045042,
              39.28263378603365
            ],
            [
              -106.05949619053195,
              39.28263376636108
            ],
            [
              -106.05949619446326,
              39.28263374708516
            ],
            [
              -106.05949620209222,
              39.28263372895188
            ],
            [
              -106.05956248618298,
              39.282511456624135
            ],
            [
              -106.05965085271419,
              39.28234844975591
            ],
            [
              -106.05964984050537,
              39.28222075707388
            ],
            [
              -106.05954434274632,
              39.282105151608796
            ],
            [
              -106.05940911475376,
              39.28201288684833
            ],
            [
              -106.05940909468956,
              39.282012868736345
            ],
            [
              -106.05932611900032,
              39.28191454151492
            ],
            [
              -106.05932611040521,
              39.28191452966894
            ],
            [
              -106.05925799201762,
              39.2818045244841
            ],
            [
              -106.05915253031041,
              39.28169471361166
            ],
            [
              -106.0590401822632,
              39.28165461906125
            ],
            [
              -106.058928475308,
              39.28169578601201
            ],
            [
              -106.05886174630201,
              39.281759971884114
            ],
            [
              -106.05886173071181,
              39.28175998415013
            ],
            [
              -106.05886171300713,
              39.28175999309741
            ],
            [
              -106.05886169388467,
              39.281759998373886
            ],
            [
              -106.05875722030426,
              39.281777919322565
            ],
            [
              -106.05875720257428,
              39.28177792075871
            ],
            [
              -106.05875718487036,
              39.28177791903081
            ],
            [
              -106.05875716775267,
              39.281777914193555
            ],
            [
              -106.05875715176283,
              39.28177790639999
            ],
            [
              -106.05865203598694,
              39.28171452754797
            ],
            [
              -106.05865202328461,
              39.28171451846552
            ],
            [
              -106.05865201215109,
              39.28171450751634
            ],
            [
              -106.05857660090463,
              39.28162775764988
            ],
            [
              -106.0585765895188,
              39.28162774160119
            ],
            [
              -106.05857658149603,
              39.28162772363365
            ],
            [
              -106.05857657714697,
              39.28162770444295
            ],
            [
              -106.0585606217732,
              39.28150001814591
            ],
            [
              -106.05856062117742,
              39.28150001167569
            ],
            [
              -106.05855200190432,
              39.28135489533668
            ],
            [
              -106.05848394718365,
              39.281250720936164
            ],
            [
              -106.05840119453467,
              39.28117565589398
            ],
            [
              -106.05828167944031,
              39.281176226766696
            ],
            [
              -106.0582816734727,
              39.28117622661703
            ],
            [
              -106.05818449039577,
              39.28117088325866
            ],
            [
              -106.05818447229618,
              39.28117088058731
            ],
            [
              -106.05818445498619,
              39.28117087466312
            ],
            [
              -106.05818443904525,
              39.28117086568437
            ],
            [
              -106.058109304383,
              39.281118958112586
            ],
            [
              -106.05810928902922,
              39.28111894503298
            ],
            [
              -106.0581092766124,
              39.2811189291384
            ],
            [
              -106.05810926763769,
              39.281118911075474
            ],
            [
              -106.0581092624702,
              39.28111889157902
            ],
            [
              -106.0580935375799,
              39.28102024146064
            ],
            [
              -106.0580935367695,
              39.28102023505087
            ],
            [
              -106.05808537637584,
              39.28093316723929
            ],
            [
              -106.05804870055496,
              39.280733277637516
            ],
            [
              -106.05804869892,
              39.28073325841136
            ],
            [
              -106.05804870100798,
              39.280733239229114
            ],
            [
              -106.05804870674112,
              39.28073322080497
            ],
            [
              -106.058048715906,
              39.28073320382489
            ],
            [
              -106.05804872816138,
              39.28073318892107
            ],
            [
              -106.05853510673512,
              39.28024624604242
            ],
            [
              -106.0585351185325,
              39.28024623593838
            ],
            [
              -106.05853513175228,
              39.28024622778316
            ],
            [
              -106.05909661954986,
              39.279957464911035
            ],
            [
              -106.05843300097891,
              39.27902255403448
            ],
            [
              -106.05843299150129,
              39.2790225375627
            ],
            [
              -106.05843298531092,
              39.279022519595394
            ],
            [
              -106.05843298263134,
              39.27902250078144
            ],
            [
              -106.05843298355936,
              39.2790224818003
            ],
            [
              -106.05843298806143,
              39.27902246333746
            ],
            [
              -106.05843299597497,
              39.27902244605971
            ],
            [
              -106.05843300701419,
              39.27902243059102
            ],
            [
              -106.05843302078041,
              39.279022417490026
            ],
            [
              -106.05843303677648,
              39.279022407229874
            ],
            [
              -106.05954653452858,
              39.27844954773887
            ],
            [
              -106.0595465540551,
              39.27844954016
            ],
            [
              -106.05954657473201,
              39.278449536814854
            ],
            [
              -106.05954659565217,
              39.27844953785021
            ],
            [
              -106.05954661589773,
              39.27844954322064
            ],
            [
              -106.0595466345805,
              39.27844955269053
            ],
            [
              -106.0595466508808,
              39.27844956584441
            ],
            [
              -106.05954666408351,
              39.278449582105196
            ],
            [
              -106.0597070378296,
              39.27869594406638
            ],
            [
              -106.05970704646751,
              39.27869596049236
            ],
            [
              -106.05970705192136,
              39.278695978231625
            ],
            [
              -106.05970705400333,
              39.27869599667319
            ],
            [
              -106.05970705264167,
              39.2786960151819
            ],
            [
              -106.05970704788331,
              39.27869603312024
            ],
            [
              -106.05970703989213,
              39.27869604987038
            ],
            [
              -106.05970702894338,
              39.27869606485541
            ],
            [
              -106.05970701541415,
              39.27869607755919
            ],
            [
              -106.05970699977041,
              39.27869608754417
            ],
            [
              -106.05925638212877,
              39.2789279189156
            ],
            [
              -106.06027244813463,
              39.280120856116426
            ],
            [
              -106.06085784518751,
              39.27981968121816
            ],
            [
              -106.06191654164266,
              39.27910725723665
            ],
            [
              -106.0619165588617,
              39.27910724795553
            ],
            [
              -106.0619165775581,
              39.27910724220405
            ],
            [
              -106.06191659701645,
              39.27910724020228
            ],
            [
              -106.06191661649223,
              39.27910724202682
            ],
            [
              -106.06191663524021,
              39.279107247607854
            ],
            [
              -106.06191665254303,
              39.27910725673183
            ],
            [
              -106.06191666773863,
              39.27910726904963
            ],
            [
              -106.06191668024557,
              39.279107284089946
            ],
            [
              -106.0619166895853,
              39.27910730127728
            ],
            [
              -106.06191669540044,
              39.279107319953965
            ],
            [
              -106.06191669746849,
              39.27910733940539
            ],
            [
              -106.06192363505579,
              39.27997903280161
            ],
            [
              -106.06425509745159,
              39.27996780150329
            ],
            [
              -106.0642551169307,
              39.27996780332322
            ],
            [
              -106.06425513568267,
              39.27996780890091
            ],
            [
              -106.06425515298982,
              39.279967818022904
            ],
            [
              -106.06425516818967,
              39.279967830340034
            ],
            [
              -106.06425518070048,
              39.27996784538088
            ],
            [
              -106.06425519004341,
              39.279967862569755
            ],
            [
              -106.06425519586084,
              39.27996788124876
            ],
            [
              -106.06425519793012,
              39.27996790070295
            ],
            [
              -106.06426967925744,
              39.28177986142568
            ],
            [
              -106.0689502940184,
              39.28178045306483
            ],
            [
              -106.06895031455893,
              39.28178045519979
            ],
            [
              -106.06895033422292,
              39.2817804615084
            ],
            [
              -106.06895035217177,
              39.28178047172163
            ],
            [
              -106.06895036764,
              39.281780485403914
            ],
            [
              -106.06895037996794,
              39.28178050197174
            ],
            [
              -106.06895038862986,
              39.28178052071854
            ],
            [
              -106.06925377727939,
              39.28266803742689
            ],
            [
              -106.06951580364363,
              39.282710752673495
            ],
            [
              -106.06951583058108,
              39.2827107611006
            ],
            [
              -106.07137533814934,
              39.28359709023251
            ],
            [
              -106.07376057055323,
              39.28355506115904
            ]
          ]
        ]
      }
    }